{
  "1": {
    "n": 1,
    "P": [
      1
    ],
    "maxP": 1,
    "ssd": true
  },
  "2": {
    "n": 2,
    "P": [
      6,
      5
    ],
    "maxP": 6,
    "ssd": true
  },
  "3": {
    "n": 3,
    "P": [
      11,
      10,
      5
    ],
    "maxP": 11,
    "ssd": true
  },
  "4": {
    "n": 4,
    "P": [
      13,
      12,
      7,
      2
    ],
    "maxP": 13,
    "ssd": true
  },
  "5": {
    "n": 5,
    "P": [
      15,
      14,
      9,
      4,
      2
    ],
    "maxP": 15,
    "ssd": false,
    "collision_optimized": "Collision detected involving 2"
  },
  "6": {
    "n": 6,
    "P": [
      19,
      18,
      13,
      8,
      6,
      4
    ],
    "maxP": 19,
    "ssd": false,
    "collision_optimized": "Collision detected involving 6"
  },
  "7": {
    "n": 7,
    "P": [
      43,
      42,
      37,
      32,
      30,
      28,
      24
    ],
    "maxP": 43,
    "ssd": false,
    "collision_optimized": "Collision detected involving 24"
  },
  "8": {
    "n": 8,
    "P": [
      77,
      76,
      71,
      66,
      64,
      62,
      58,
      34
    ],
    "maxP": 77,
    "ssd": false,
    "collision_optimized": "Collision detected involving 58"
  },
  "9": {
    "n": 9,
    "P": [
      144,
      143,
      138,
      133,
      131,
      129,
      125,
      101,
      67
    ],
    "maxP": 144,
    "ssd": false,
    "collision_optimized": "Collision detected involving 125"
  },
  "10": {
    "n": 10,
    "P": [
      275,
      274,
      269,
      264,
      262,
      260,
      256,
      232,
      198,
      131
    ],
    "maxP": 275,
    "ssd": false,
    "collision_optimized": "Collision detected involving 256"
  },
  "11": {
    "n": 11,
    "P": [
      535,
      534,
      529,
      524,
      522,
      520,
      516,
      492,
      458,
      391,
      260
    ],
    "maxP": 535,
    "ssd": false,
    "collision_optimized": "Collision detected involving 516"
  },
  "12": {
    "n": 12,
    "P": [
      1051,
      1050,
      1045,
      1040,
      1038,
      1036,
      1032,
      1008,
      974,
      907,
      776,
      516
    ],
    "maxP": 1051,
    "ssd": false,
    "collision_optimized": "Collision detected involving 1032"
  },
  "13": {
    "n": 13,
    "P": [
      2059,
      2058,
      2053,
      2048,
      2046,
      2044,
      2040,
      2016,
      1982,
      1915,
      1784,
      1524,
      1008
    ],
    "maxP": 2059,
    "ssd": false,
    "collision_optimized": "Collision detected involving 2040"
  },
  "14": {
    "n": 14,
    "P": [
      4075,
      4074,
      4069,
      4064,
      4062,
      4060,
      4056,
      4032,
      3998,
      3931,
      3800,
      3540,
      3024,
      2016
    ],
    "maxP": 4075,
    "ssd": false,
    "collision_optimized": "Collision detected involving 4056"
  },
  "15": {
    "n": 15,
    "P": [
      8073,
      8072,
      8067,
      8062,
      8060,
      8058,
      8054,
      8030,
      7996,
      7929,
      7798,
      7538,
      7022,
      6014,
      3998
    ],
    "maxP": 8073,
    "ssd": false,
    "collision_optimized": "Collision detected involving 8054"
  },
  "16": {
    "n": 16,
    "P": [
      16002,
      16001,
      15996,
      15991,
      15989,
      15987,
      15983,
      15959,
      15925,
      15858,
      15727,
      15467,
      14951,
      13943,
      11927,
      7929
    ],
    "maxP": 16002,
    "ssd": false,
    "collision_optimized": "Collision detected involving 15983"
  },
  "17": {
    "n": 17,
    "P": [
      31729,
      31728,
      31723,
      31718,
      31716,
      31714,
      31710,
      31686,
      31652,
      31585,
      31454,
      31194,
      30678,
      29670,
      27654,
      23656,
      15727
    ],
    "maxP": 31729,
    "ssd": false,
    "collision_optimized": "Collision detected involving 31710"
  },
  "18": {
    "n": 18,
    "P": [
      62923,
      62922,
      62917,
      62912,
      62910,
      62908,
      62904,
      62880,
      62846,
      62779,
      62648,
      62388,
      61872,
      60864,
      58848,
      54850,
      46921,
      31194
    ],
    "maxP": 62923,
    "ssd": false,
    "collision_optimized": "Collision detected involving 62904"
  },
  "19": {
    "n": 19,
    "P": [
      124795,
      124794,
      124789,
      124784,
      124782,
      124780,
      124776,
      124752,
      124718,
      124651,
      124520,
      124260,
      123744,
      122736,
      120720,
      116722,
      108793,
      93066,
      61872
    ],
    "maxP": 124795,
    "ssd": false,
    "collision_optimized": "Collision detected involving 124776"
  },
  "20": {
    "n": 20,
    "P": [
      248539,
      248538,
      248533,
      248528,
      248526,
      248524,
      248520,
      248496,
      248462,
      248395,
      248264,
      248004,
      247488,
      246480,
      244464,
      240466,
      232537,
      216810,
      185616,
      123744
    ],
    "maxP": 248539,
    "ssd": false,
    "collision_optimized": "Collision detected involving 248520"
  },
  "21": {
    "n": 21,
    "P": [
      495019,
      495018,
      495013,
      495008,
      495006,
      495004,
      495000,
      494976,
      494942,
      494875,
      494744,
      494484,
      493968,
      492960,
      490944,
      486946,
      479017,
      463290,
      432096,
      370224,
      246480
    ],
    "maxP": 495019,
    "ssd": false,
    "collision_optimized": "Collision detected involving 495000"
  },
  "22": {
    "n": 22,
    "P": [
      985963,
      985962,
      985957,
      985952,
      985950,
      985948,
      985944,
      985920,
      985886,
      985819,
      985688,
      985428,
      984912,
      983904,
      981888,
      977890,
      969961,
      954234,
      923040,
      861168,
      737424,
      490944
    ],
    "maxP": 985963,
    "ssd": false,
    "collision_optimized": "Collision detected involving 985944"
  },
  "23": {
    "n": 23,
    "P": [
      1963853,
      1963852,
      1963847,
      1963842,
      1963840,
      1963838,
      1963834,
      1963810,
      1963776,
      1963709,
      1963578,
      1963318,
      1962802,
      1961794,
      1959778,
      1955780,
      1947851,
      1932124,
      1900930,
      1839058,
      1715314,
      1468834,
      977890
    ],
    "maxP": 1963853,
    "ssd": false,
    "collision_optimized": "Collision detected involving 1963834"
  },
  "24": {
    "n": 24,
    "P": [
      3911704,
      3911703,
      3911698,
      3911693,
      3911691,
      3911689,
      3911685,
      3911661,
      3911627,
      3911560,
      3911429,
      3911169,
      3910653,
      3909645,
      3907629,
      3903631,
      3895702,
      3879975,
      3848781,
      3786909,
      3663165,
      3416685,
      2925741,
      1947851
    ],
    "maxP": 3911704,
    "ssd": false,
    "collision_optimized": "Collision detected involving 3911685"
  },
  "25": {
    "n": 25,
    "P": [
      7791679,
      7791678,
      7791673,
      7791668,
      7791666,
      7791664,
      7791660,
      7791636,
      7791602,
      7791535,
      7791404,
      7791144,
      7790628,
      7789620,
      7787604,
      7783606,
      7775677,
      7759950,
      7728756,
      7666884,
      7543140,
      7296660,
      6805716,
      5827826,
      3879975
    ],
    "maxP": 7791679,
    "ssd": false,
    "collision_optimized": "Collision detected involving 7791660"
  },
  "26": {
    "n": 26,
    "P": [
      15520435,
      15520434,
      15520429,
      15520424,
      15520422,
      15520420,
      15520416,
      15520392,
      15520358,
      15520291,
      15520160,
      15519900,
      15519384,
      15518376,
      15516360,
      15512362,
      15504433,
      15488706,
      15457512,
      15395640,
      15271896,
      15025416,
      14534472,
      13556582,
      11608731,
      7728756
    ],
    "maxP": 15520435,
    "ssd": false,
    "collision_optimized": "Collision detected involving 15520416"
  },
  "27": {
    "n": 27,
    "P": [
      30977947,
      30977946,
      30977941,
      30977936,
      30977934,
      30977932,
      30977928,
      30977904,
      30977870,
      30977803,
      30977672,
      30977412,
      30976896,
      30975888,
      30973872,
      30969874,
      30961945,
      30946218,
      30915024,
      30853152,
      30729408,
      30482928,
      29991984,
      29014094,
      27066243,
      23186268,
      15457512
    ],
    "maxP": 30977947,
    "ssd": false,
    "collision_optimized": "Collision detected involving 30977928"
  },
  "28": {
    "n": 28,
    "P": [
      61831099,
      61831098,
      61831093,
      61831088,
      61831086,
      61831084,
      61831080,
      61831056,
      61831022,
      61830955,
      61830824,
      61830564,
      61830048,
      61829040,
      61827024,
      61823026,
      61815097,
      61799370,
      61768176,
      61706304,
      61582560,
      61336080,
      60845136,
      59867246,
      57919395,
      54039420,
      46310664,
      30853152
    ],
    "maxP": 61831099,
    "ssd": false,
    "collision_optimized": "Collision detected involving 61831080"
  },
  "29": {
    "n": 29,
    "P": [
      123413659,
      123413658,
      123413653,
      123413648,
      123413646,
      123413644,
      123413640,
      123413616,
      123413582,
      123413515,
      123413384,
      123413124,
      123412608,
      123411600,
      123409584,
      123405586,
      123397657,
      123381930,
      123350736,
      123288864,
      123165120,
      122918640,
      122427696,
      121449806,
      119501955,
      115621980,
      107893224,
      92435712,
      61582560
    ],
    "maxP": 123413659,
    "ssd": false,
    "collision_optimized": "Collision detected involving 123413640"
  },
  "30": {
    "n": 30,
    "P": [
      246332299,
      246332298,
      246332293,
      246332288,
      246332286,
      246332284,
      246332280,
      246332256,
      246332222,
      246332155,
      246332024,
      246331764,
      246331248,
      246330240,
      246328224,
      246324226,
      246316297,
      246300570,
      246269376,
      246207504,
      246083760,
      245837280,
      245346336,
      244368446,
      242420595,
      238540620,
      230811864,
      215354352,
      184501200,
      122918640
    ],
    "maxP": 246332299,
    "ssd": false,
    "collision_optimized": "Collision detected involving 246332280"
  }
}