{
  "1": {
    "n": 1,
    "P": [
      1
    ],
    "maxP": 1,
    "ssd": true
  },
  "2": {
    "n": 2,
    "P": [
      2,
      1
    ],
    "maxP": 2,
    "ssd": true
  },
  "3": {
    "n": 3,
    "P": [
      5,
      4,
      3
    ],
    "maxP": 5,
    "ssd": true
  },
  "4": {
    "n": 4,
    "P": [
      8,
      7,
      6,
      3
    ],
    "maxP": 8,
    "ssd": true
  },
  "5": {
    "n": 5,
    "P": [
      15,
      14,
      13,
      10,
      7
    ],
    "maxP": 15,
    "ssd": true
  },
  "6": {
    "n": 6,
    "P": [
      28,
      27,
      26,
      23,
      20,
      13
    ],
    "maxP": 28,
    "ssd": true
  },
  "7": {
    "n": 7,
    "P": [
      51,
      50,
      49,
      46,
      43,
      36,
      23
    ],
    "maxP": 51,
    "ssd": true
  },
  "8": {
    "n": 8,
    "P": [
      97,
      96,
      95,
      92,
      89,
      82,
      69,
      46
    ],
    "maxP": 97,
    "ssd": true
  },
  "9": {
    "n": 9,
    "P": [
      186,
      185,
      184,
      181,
      178,
      171,
      158,
      135,
      89
    ],
    "maxP": 186,
    "ssd": true
  },
  "10": {
    "n": 10,
    "P": [
      357,
      356,
      355,
      352,
      349,
      342,
      329,
      306,
      260,
      171
    ],
    "maxP": 357,
    "ssd": true
  },
  "11": {
    "n": 11,
    "P": [
      686,
      685,
      684,
      681,
      678,
      671,
      658,
      635,
      589,
      500,
      329
    ],
    "maxP": 686,
    "ssd": true
  },
  "12": {
    "n": 12,
    "P": [
      1344,
      1343,
      1342,
      1339,
      1336,
      1329,
      1316,
      1293,
      1247,
      1158,
      987,
      658
    ],
    "maxP": 1344,
    "ssd": true
  },
  "13": {
    "n": 13,
    "P": [
      2637,
      2636,
      2635,
      2632,
      2629,
      2622,
      2609,
      2586,
      2540,
      2451,
      2280,
      1951,
      1293
    ],
    "maxP": 2637,
    "ssd": true
  },
  "14": {
    "n": 14,
    "P": [
      5177,
      5176,
      5175,
      5172,
      5169,
      5162,
      5149,
      5126,
      5080,
      4991,
      4820,
      4491,
      3833,
      2540
    ],
    "maxP": 5177,
    "ssd": true
  },
  "15": {
    "n": 15,
    "P": [
      10168,
      10167,
      10166,
      10163,
      10160,
      10153,
      10140,
      10117,
      10071,
      9982,
      9811,
      9482,
      8824,
      7531,
      4991
    ],
    "maxP": 10168,
    "ssd": true
  },
  "16": {
    "n": 16,
    "P": [
      19979,
      19978,
      19977,
      19974,
      19971,
      19964,
      19951,
      19928,
      19882,
      19793,
      19622,
      19293,
      18635,
      17342,
      14802,
      9811
    ],
    "maxP": 19979,
    "ssd": true
  },
  "17": {
    "n": 17,
    "P": [
      39601,
      39600,
      39599,
      39596,
      39593,
      39586,
      39573,
      39550,
      39504,
      39415,
      39244,
      38915,
      38257,
      36964,
      34424,
      29433,
      19622
    ],
    "maxP": 39601,
    "ssd": true
  },
  "18": {
    "n": 18,
    "P": [
      78516,
      78515,
      78514,
      78511,
      78508,
      78501,
      78488,
      78465,
      78419,
      78330,
      78159,
      77830,
      77172,
      75879,
      73339,
      68348,
      58537,
      38915
    ],
    "maxP": 78516,
    "ssd": true
  },
  "19": {
    "n": 19,
    "P": [
      155688,
      155687,
      155686,
      155683,
      155680,
      155673,
      155660,
      155637,
      155591,
      155502,
      155331,
      155002,
      154344,
      153051,
      150511,
      145520,
      135709,
      116087,
      77172
    ],
    "maxP": 155688,
    "ssd": true
  },
  "20": {
    "n": 20,
    "P": [
      308739,
      308738,
      308737,
      308734,
      308731,
      308724,
      308711,
      308688,
      308642,
      308553,
      308382,
      308053,
      307395,
      306102,
      303562,
      298571,
      288760,
      269138,
      230223,
      153051
    ],
    "maxP": 308739,
    "ssd": true
  },
  "21": {
    "n": 21,
    "P": [
      612301,
      612300,
      612299,
      612296,
      612293,
      612286,
      612273,
      612250,
      612204,
      612115,
      611944,
      611615,
      610957,
      609664,
      607124,
      602133,
      592322,
      572700,
      533785,
      456613,
      303562
    ],
    "maxP": 612301,
    "ssd": true
  },
  "22": {
    "n": 22,
    "P": [
      1214434,
      1214433,
      1214432,
      1214429,
      1214426,
      1214419,
      1214406,
      1214383,
      1214337,
      1214248,
      1214077,
      1213748,
      1213090,
      1211797,
      1209257,
      1204266,
      1194455,
      1174833,
      1135918,
      1058746,
      905695,
      602133
    ],
    "maxP": 1214434,
    "ssd": true
  },
  "23": {
    "n": 23,
    "P": [
      2418700,
      2418699,
      2418698,
      2418695,
      2418692,
      2418685,
      2418672,
      2418649,
      2418603,
      2418514,
      2418343,
      2418014,
      2417356,
      2416063,
      2413523,
      2408532,
      2398721,
      2379099,
      2340184,
      2263012,
      2109961,
      1806399,
      1204266
    ],
    "maxP": 2418700,
    "ssd": true
  },
  "24": {
    "n": 24,
    "P": [
      4817421,
      4817420,
      4817419,
      4817416,
      4817413,
      4817406,
      4817393,
      4817370,
      4817324,
      4817235,
      4817064,
      4816735,
      4816077,
      4814784,
      4812244,
      4807253,
      4797442,
      4777820,
      4738905,
      4661733,
      4508682,
      4205120,
      3602987,
      2398721
    ],
    "maxP": 4817421,
    "ssd": true
  },
  "25": {
    "n": 25,
    "P": [
      9595241,
      9595240,
      9595239,
      9595236,
      9595233,
      9595226,
      9595213,
      9595190,
      9595144,
      9595055,
      9594884,
      9594555,
      9593897,
      9592604,
      9590064,
      9585073,
      9575262,
      9555640,
      9516725,
      9439553,
      9286502,
      8982940,
      8380807,
      7176541,
      4777820
    ],
    "maxP": 9595241,
    "ssd": true
  },
  "26": {
    "n": 26,
    "P": [
      19111966,
      19111965,
      19111964,
      19111961,
      19111958,
      19111951,
      19111938,
      19111915,
      19111869,
      19111780,
      19111609,
      19111280,
      19110622,
      19109329,
      19106789,
      19101798,
      19091987,
      19072365,
      19033450,
      18956278,
      18803227,
      18499665,
      17897532,
      16693266,
      14294545,
      9516725
    ],
    "maxP": 19111966,
    "ssd": true
  },
  "27": {
    "n": 27,
    "P": [
      38068244,
      38068243,
      38068242,
      38068239,
      38068236,
      38068229,
      38068216,
      38068193,
      38068147,
      38068058,
      38067887,
      38067558,
      38066900,
      38065607,
      38063067,
      38058076,
      38048265,
      38028643,
      37989728,
      37912556,
      37759505,
      37455943,
      36853810,
      35649544,
      33250823,
      28473003,
      18956278
    ],
    "maxP": 38068244,
    "ssd": true
  },
  "28": {
    "n": 28,
    "P": [
      75827749,
      75827748,
      75827747,
      75827744,
      75827741,
      75827734,
      75827721,
      75827698,
      75827652,
      75827563,
      75827392,
      75827063,
      75826405,
      75825112,
      75822572,
      75817581,
      75807770,
      75788148,
      75749233,
      75672061,
      75519010,
      75215448,
      74613315,
      73409049,
      71010328,
      66232508,
      56715783,
      37759505
    ],
    "maxP": 75827749,
    "ssd": true
  },
  "29": {
    "n": 29,
    "P": [
      151043197,
      151043196,
      151043195,
      151043192,
      151043189,
      151043182,
      151043169,
      151043146,
      151043100,
      151043011,
      151042840,
      151042511,
      151041853,
      151040560,
      151038020,
      151033029,
      151023218,
      151003596,
      150964681,
      150887509,
      150734458,
      150430896,
      149828763,
      148624497,
      146225776,
      141447956,
      131931231,
      112974953,
      75215448
    ],
    "maxP": 151043197,
    "ssd": true
  },
  "30": {
    "n": 30,
    "P": [
      301474093,
      301474092,
      301474091,
      301474088,
      301474085,
      301474078,
      301474065,
      301474042,
      301473996,
      301473907,
      301473736,
      301473407,
      301472749,
      301471456,
      301468916,
      301463925,
      301454114,
      301434492,
      301395577,
      301318405,
      301165354,
      300861792,
      300259659,
      299055393,
      296656672,
      291878852,
      282362127,
      263405849,
      225646344,
      150430896
    ],
    "maxP": 301474093,
    "ssd": true
  }
}