{
  "1": {
    "n": 1,
    "P": [
      3
    ],
    "maxP": 3,
    "ssd": true
  },
  "2": {
    "n": 2,
    "P": [
      7,
      4
    ],
    "maxP": 7,
    "ssd": true
  },
  "3": {
    "n": 3,
    "P": [
      12,
      9,
      5
    ],
    "maxP": 12,
    "ssd": true
  },
  "4": {
    "n": 4,
    "P": [
      13,
      10,
      6,
      1
    ],
    "maxP": 13,
    "ssd": true
  },
  "5": {
    "n": 5,
    "P": [
      14,
      11,
      7,
      2,
      1
    ],
    "maxP": 14,
    "ssd": false,
    "collision_optimized": "Collision detected involving 1"
  },
  "6": {
    "n": 6,
    "P": [
      16,
      13,
      9,
      4,
      3,
      2
    ],
    "maxP": 16,
    "ssd": false,
    "collision_optimized": "Collision detected involving 4"
  },
  "7": {
    "n": 7,
    "P": [
      37,
      34,
      30,
      25,
      24,
      23,
      21
    ],
    "maxP": 37,
    "ssd": false,
    "collision_optimized": "Collision detected involving 21"
  },
  "8": {
    "n": 8,
    "P": [
      67,
      64,
      60,
      55,
      54,
      53,
      51,
      30
    ],
    "maxP": 67,
    "ssd": false,
    "collision_optimized": "Collision detected involving 51"
  },
  "9": {
    "n": 9,
    "P": [
      126,
      123,
      119,
      114,
      113,
      112,
      110,
      89,
      59
    ],
    "maxP": 126,
    "ssd": false,
    "collision_optimized": "Collision detected involving 110"
  },
  "10": {
    "n": 10,
    "P": [
      239,
      236,
      232,
      227,
      226,
      225,
      223,
      202,
      172,
      113
    ],
    "maxP": 239,
    "ssd": false,
    "collision_optimized": "Collision detected involving 223"
  },
  "11": {
    "n": 11,
    "P": [
      465,
      462,
      458,
      453,
      452,
      451,
      449,
      428,
      398,
      339,
      226
    ],
    "maxP": 465,
    "ssd": false,
    "collision_optimized": "Collision detected involving 449"
  },
  "12": {
    "n": 12,
    "P": [
      916,
      913,
      909,
      904,
      903,
      902,
      900,
      879,
      849,
      790,
      677,
      451
    ],
    "maxP": 916,
    "ssd": false,
    "collision_optimized": "Collision detected involving 900"
  },
  "13": {
    "n": 13,
    "P": [
      1796,
      1793,
      1789,
      1784,
      1783,
      1782,
      1780,
      1759,
      1729,
      1670,
      1557,
      1331,
      880
    ],
    "maxP": 1796,
    "ssd": false,
    "collision_optimized": "Collision detected involving 1780"
  },
  "14": {
    "n": 14,
    "P": [
      3555,
      3552,
      3548,
      3543,
      3542,
      3541,
      3539,
      3518,
      3488,
      3429,
      3316,
      3090,
      2639,
      1759
    ],
    "maxP": 3555,
    "ssd": false,
    "collision_optimized": "Collision detected involving 3539"
  },
  "15": {
    "n": 15,
    "P": [
      7043,
      7040,
      7036,
      7031,
      7030,
      7029,
      7027,
      7006,
      6976,
      6917,
      6804,
      6578,
      6127,
      5247,
      3488
    ],
    "maxP": 7043,
    "ssd": false,
    "collision_optimized": "Collision detected involving 7027"
  },
  "16": {
    "n": 16,
    "P": [
      13960,
      13957,
      13953,
      13948,
      13947,
      13946,
      13944,
      13923,
      13893,
      13834,
      13721,
      13495,
      13044,
      12164,
      10405,
      6917
    ],
    "maxP": 13960,
    "ssd": false,
    "collision_optimized": "Collision detected involving 13944"
  },
  "17": {
    "n": 17,
    "P": [
      27681,
      27678,
      27674,
      27669,
      27668,
      27667,
      27665,
      27644,
      27614,
      27555,
      27442,
      27216,
      26765,
      25885,
      24126,
      20638,
      13721
    ],
    "maxP": 27681,
    "ssd": false,
    "collision_optimized": "Collision detected involving 27665"
  },
  "18": {
    "n": 18,
    "P": [
      54897,
      54894,
      54890,
      54885,
      54884,
      54883,
      54881,
      54860,
      54830,
      54771,
      54658,
      54432,
      53981,
      53101,
      51342,
      47854,
      40937,
      27216
    ],
    "maxP": 54897,
    "ssd": false,
    "collision_optimized": "Collision detected involving 54881"
  },
  "19": {
    "n": 19,
    "P": [
      108878,
      108875,
      108871,
      108866,
      108865,
      108864,
      108862,
      108841,
      108811,
      108752,
      108639,
      108413,
      107962,
      107082,
      105323,
      101835,
      94918,
      81197,
      53981
    ],
    "maxP": 108878,
    "ssd": false,
    "collision_optimized": "Collision detected involving 108862"
  },
  "20": {
    "n": 20,
    "P": [
      217291,
      217288,
      217284,
      217279,
      217278,
      217277,
      217275,
      217254,
      217224,
      217165,
      217052,
      216826,
      216375,
      215495,
      213736,
      210248,
      203331,
      189610,
      162394,
      108413
    ],
    "maxP": 217291,
    "ssd": false,
    "collision_optimized": "Collision detected involving 217275"
  },
  "21": {
    "n": 21,
    "P": [
      432786,
      432783,
      432779,
      432774,
      432773,
      432772,
      432770,
      432749,
      432719,
      432660,
      432547,
      432321,
      431870,
      430990,
      429231,
      425743,
      418826,
      405105,
      377889,
      323908,
      215495
    ],
    "maxP": 432786,
    "ssd": false,
    "collision_optimized": "Collision detected involving 432770"
  },
  "22": {
    "n": 22,
    "P": [
      862017,
      862014,
      862010,
      862005,
      862004,
      862003,
      862001,
      861980,
      861950,
      861891,
      861778,
      861552,
      861101,
      860221,
      858462,
      854974,
      848057,
      834336,
      807120,
      753139,
      644726,
      429231
    ],
    "maxP": 862017,
    "ssd": false,
    "collision_optimized": "Collision detected involving 862001"
  },
  "23": {
    "n": 23,
    "P": [
      1716991,
      1716988,
      1716984,
      1716979,
      1716978,
      1716977,
      1716975,
      1716954,
      1716924,
      1716865,
      1716752,
      1716526,
      1716075,
      1715195,
      1713436,
      1709948,
      1703031,
      1689310,
      1662094,
      1608113,
      1499700,
      1284205,
      854974
    ],
    "maxP": 1716991,
    "ssd": false,
    "collision_optimized": "Collision detected involving 1716975"
  },
  "24": {
    "n": 24,
    "P": [
      3420022,
      3420019,
      3420015,
      3420010,
      3420009,
      3420008,
      3420006,
      3419985,
      3419955,
      3419896,
      3419783,
      3419557,
      3419106,
      3418226,
      3416467,
      3412979,
      3406062,
      3392341,
      3365125,
      3311144,
      3202731,
      2987236,
      2558005,
      1703031
    ],
    "maxP": 3420022,
    "ssd": false,
    "collision_optimized": "Collision detected involving 3420006"
  },
  "25": {
    "n": 25,
    "P": [
      6812363,
      6812360,
      6812356,
      6812351,
      6812350,
      6812349,
      6812347,
      6812326,
      6812296,
      6812237,
      6812124,
      6811898,
      6811447,
      6810567,
      6808808,
      6805320,
      6798403,
      6784682,
      6757466,
      6703485,
      6595072,
      6379577,
      5950346,
      5095372,
      3392341
    ],
    "maxP": 6812363,
    "ssd": false,
    "collision_optimized": "Collision detected involving 6812347"
  },
  "26": {
    "n": 26,
    "P": [
      13597045,
      13597042,
      13597038,
      13597033,
      13597032,
      13597031,
      13597029,
      13597008,
      13596978,
      13596919,
      13596806,
      13596580,
      13596129,
      13595249,
      13593490,
      13590002,
      13583085,
      13569364,
      13542148,
      13488167,
      13379754,
      13164259,
      12735028,
      11880054,
      10177023,
      6784682
    ],
    "maxP": 13597045,
    "ssd": false,
    "collision_optimized": "Collision detected involving 13597029"
  },
  "27": {
    "n": 27,
    "P": [
      27139193,
      27139190,
      27139186,
      27139181,
      27139180,
      27139179,
      27139177,
      27139156,
      27139126,
      27139067,
      27138954,
      27138728,
      27138277,
      27137397,
      27135638,
      27132150,
      27125233,
      27111512,
      27084296,
      27030315,
      26921902,
      26706407,
      26277176,
      25422202,
      23719171,
      20326830,
      13542148
    ],
    "maxP": 27139193,
    "ssd": false,
    "collision_optimized": "Collision detected involving 27139177"
  },
  "28": {
    "n": 28,
    "P": [
      54169508,
      54169505,
      54169501,
      54169496,
      54169495,
      54169494,
      54169492,
      54169471,
      54169441,
      54169382,
      54169269,
      54169043,
      54168592,
      54167712,
      54165953,
      54162465,
      54155548,
      54141827,
      54114611,
      54060630,
      53952217,
      53736722,
      53307491,
      52452517,
      50749486,
      47357145,
      40572463,
      27030315
    ],
    "maxP": 54169508,
    "ssd": false,
    "collision_optimized": "Collision detected involving 54169492"
  },
  "29": {
    "n": 29,
    "P": [
      108121725,
      108121722,
      108121718,
      108121713,
      108121712,
      108121711,
      108121709,
      108121688,
      108121658,
      108121599,
      108121486,
      108121260,
      108120809,
      108119929,
      108118170,
      108114682,
      108107765,
      108094044,
      108066828,
      108012847,
      107904434,
      107688939,
      107259708,
      106404734,
      104701703,
      101309362,
      94524680,
      80982532,
      53952217
    ],
    "maxP": 108121725,
    "ssd": false,
    "collision_optimized": "Collision detected involving 108121709"
  },
  "30": {
    "n": 30,
    "P": [
      215810664,
      215810661,
      215810657,
      215810652,
      215810651,
      215810650,
      215810648,
      215810627,
      215810597,
      215810538,
      215810425,
      215810199,
      215809748,
      215808868,
      215807109,
      215803621,
      215796704,
      215782983,
      215755767,
      215701786,
      215593373,
      215377878,
      214948647,
      214093673,
      212390642,
      208998301,
      202213619,
      188671471,
      161641156,
      107688939
    ],
    "maxP": 215810664,
    "ssd": false,
    "collision_optimized": "Collision detected involving 215810648"
  }
}