{
  "1": {
    "n": 1,
    "P": [
      3
    ],
    "maxP": 3,
    "ssd": true
  },
  "2": {
    "n": 2,
    "P": [
      4,
      1
    ],
    "maxP": 4,
    "ssd": true
  },
  "3": {
    "n": 3,
    "P": [
      5,
      2,
      1
    ],
    "maxP": 5,
    "ssd": true
  },
  "4": {
    "n": 4,
    "P": [
      7,
      4,
      3,
      2
    ],
    "maxP": 7,
    "ssd": false,
    "collision_optimized": "Collision detected involving 3"
  },
  "5": {
    "n": 5,
    "P": [
      14,
      11,
      10,
      9,
      7
    ],
    "maxP": 14,
    "ssd": false,
    "collision_optimized": "Collision detected involving 7"
  },
  "6": {
    "n": 6,
    "P": [
      24,
      21,
      20,
      19,
      17,
      10
    ],
    "maxP": 24,
    "ssd": false,
    "collision_optimized": "Collision detected involving 17"
  },
  "7": {
    "n": 7,
    "P": [
      44,
      41,
      40,
      39,
      37,
      30,
      20
    ],
    "maxP": 44,
    "ssd": false,
    "collision_optimized": "Collision detected involving 37"
  },
  "8": {
    "n": 8,
    "P": [
      83,
      80,
      79,
      78,
      76,
      69,
      59,
      39
    ],
    "maxP": 83,
    "ssd": false,
    "collision_optimized": "Collision detected involving 76"
  },
  "9": {
    "n": 9,
    "P": [
      159,
      156,
      155,
      154,
      152,
      145,
      135,
      115,
      76
    ],
    "maxP": 159,
    "ssd": false,
    "collision_optimized": "Collision detected involving 152"
  },
  "10": {
    "n": 10,
    "P": [
      304,
      301,
      300,
      299,
      297,
      290,
      280,
      260,
      221,
      145
    ],
    "maxP": 304,
    "ssd": false,
    "collision_optimized": "Collision detected involving 297"
  },
  "11": {
    "n": 11,
    "P": [
      594,
      591,
      590,
      589,
      587,
      580,
      570,
      550,
      511,
      435,
      290
    ],
    "maxP": 594,
    "ssd": false,
    "collision_optimized": "Collision detected involving 587"
  },
  "12": {
    "n": 12,
    "P": [
      1164,
      1161,
      1160,
      1159,
      1157,
      1150,
      1140,
      1120,
      1081,
      1005,
      860,
      570
    ],
    "maxP": 1164,
    "ssd": false,
    "collision_optimized": "Collision detected involving 1157"
  },
  "13": {
    "n": 13,
    "P": [
      2284,
      2281,
      2280,
      2279,
      2277,
      2270,
      2260,
      2240,
      2201,
      2125,
      1980,
      1690,
      1120
    ],
    "maxP": 2284,
    "ssd": false,
    "collision_optimized": "Collision detected involving 2277"
  },
  "14": {
    "n": 14,
    "P": [
      4485,
      4482,
      4481,
      4480,
      4478,
      4471,
      4461,
      4441,
      4402,
      4326,
      4181,
      3891,
      3321,
      2201
    ],
    "maxP": 4485,
    "ssd": false,
    "collision_optimized": "Collision detected involving 4478"
  },
  "15": {
    "n": 15,
    "P": [
      8811,
      8808,
      8807,
      8806,
      8804,
      8797,
      8787,
      8767,
      8728,
      8652,
      8507,
      8217,
      7647,
      6527,
      4326
    ],
    "maxP": 8811,
    "ssd": false,
    "collision_optimized": "Collision detected involving 8804"
  },
  "16": {
    "n": 16,
    "P": [
      17463,
      17460,
      17459,
      17458,
      17456,
      17449,
      17439,
      17419,
      17380,
      17304,
      17159,
      16869,
      16299,
      15179,
      12978,
      8652
    ],
    "maxP": 17463,
    "ssd": false,
    "collision_optimized": "Collision detected involving 17456"
  },
  "17": {
    "n": 17,
    "P": [
      34622,
      34619,
      34618,
      34617,
      34615,
      34608,
      34598,
      34578,
      34539,
      34463,
      34318,
      34028,
      33458,
      32338,
      30137,
      25811,
      17159
    ],
    "maxP": 34622,
    "ssd": false,
    "collision_optimized": "Collision detected involving 34615"
  },
  "18": {
    "n": 18,
    "P": [
      68650,
      68647,
      68646,
      68645,
      68643,
      68636,
      68626,
      68606,
      68567,
      68491,
      68346,
      68056,
      67486,
      66366,
      64165,
      59839,
      51187,
      34028
    ],
    "maxP": 68650,
    "ssd": false,
    "collision_optimized": "Collision detected involving 68643"
  },
  "19": {
    "n": 19,
    "P": [
      136136,
      136133,
      136132,
      136131,
      136129,
      136122,
      136112,
      136092,
      136053,
      135977,
      135832,
      135542,
      134972,
      133852,
      131651,
      127325,
      118673,
      101514,
      67486
    ],
    "maxP": 136136,
    "ssd": false,
    "collision_optimized": "Collision detected involving 136129"
  },
  "20": {
    "n": 20,
    "P": [
      269988,
      269985,
      269984,
      269983,
      269981,
      269974,
      269964,
      269944,
      269905,
      269829,
      269684,
      269394,
      268824,
      267704,
      265503,
      261177,
      252525,
      235366,
      201338,
      133852
    ],
    "maxP": 269988,
    "ssd": false,
    "collision_optimized": "Collision detected involving 269981"
  },
  "21": {
    "n": 21,
    "P": [
      535491,
      535488,
      535487,
      535486,
      535484,
      535477,
      535467,
      535447,
      535408,
      535332,
      535187,
      534897,
      534327,
      533207,
      531006,
      526680,
      518028,
      500869,
      466841,
      399355,
      265503
    ],
    "maxP": 535491,
    "ssd": false,
    "collision_optimized": "Collision detected involving 535484"
  },
  "22": {
    "n": 22,
    "P": [
      1066497,
      1066494,
      1066493,
      1066492,
      1066490,
      1066483,
      1066473,
      1066453,
      1066414,
      1066338,
      1066193,
      1065903,
      1065333,
      1064213,
      1062012,
      1057686,
      1049034,
      1031875,
      997847,
      930361,
      796509,
      531006
    ],
    "maxP": 1066497,
    "ssd": false,
    "collision_optimized": "Collision detected involving 1066490"
  },
  "23": {
    "n": 23,
    "P": [
      2124183,
      2124180,
      2124179,
      2124178,
      2124176,
      2124169,
      2124159,
      2124139,
      2124100,
      2124024,
      2123879,
      2123589,
      2123019,
      2121899,
      2119698,
      2115372,
      2106720,
      2089561,
      2055533,
      1988047,
      1854195,
      1588692,
      1057686
    ],
    "maxP": 2124183,
    "ssd": false,
    "collision_optimized": "Collision detected involving 2124176"
  },
  "24": {
    "n": 24,
    "P": [
      4230903,
      4230900,
      4230899,
      4230898,
      4230896,
      4230889,
      4230879,
      4230859,
      4230820,
      4230744,
      4230599,
      4230309,
      4229739,
      4228619,
      4226418,
      4222092,
      4213440,
      4196281,
      4162253,
      4094767,
      3960915,
      3695412,
      3164406,
      2106720
    ],
    "maxP": 4230903,
    "ssd": false,
    "collision_optimized": "Collision detected involving 4230896"
  },
  "25": {
    "n": 25,
    "P": [
      8427184,
      8427181,
      8427180,
      8427179,
      8427177,
      8427170,
      8427160,
      8427140,
      8427101,
      8427025,
      8426880,
      8426590,
      8426020,
      8424900,
      8422699,
      8418373,
      8409721,
      8392562,
      8358534,
      8291048,
      8157196,
      7891693,
      7360687,
      6303001,
      4196281
    ],
    "maxP": 8427184,
    "ssd": false,
    "collision_optimized": "Collision detected involving 8427177"
  },
  "26": {
    "n": 26,
    "P": [
      16785718,
      16785715,
      16785714,
      16785713,
      16785711,
      16785704,
      16785694,
      16785674,
      16785635,
      16785559,
      16785414,
      16785124,
      16784554,
      16783434,
      16781233,
      16776907,
      16768255,
      16751096,
      16717068,
      16649582,
      16515730,
      16250227,
      15719221,
      14661535,
      12554815,
      8358534
    ],
    "maxP": 16785718,
    "ssd": false,
    "collision_optimized": "Collision detected involving 16785711"
  },
  "27": {
    "n": 27,
    "P": [
      33435300,
      33435297,
      33435296,
      33435295,
      33435293,
      33435286,
      33435276,
      33435256,
      33435217,
      33435141,
      33434996,
      33434706,
      33434136,
      33433016,
      33430815,
      33426489,
      33417837,
      33400678,
      33366650,
      33299164,
      33165312,
      32899809,
      32368803,
      31311117,
      29204397,
      25008116,
      16649582
    ],
    "maxP": 33435300,
    "ssd": false,
    "collision_optimized": "Collision detected involving 33435293"
  },
  "28": {
    "n": 28,
    "P": [
      66600612,
      66600609,
      66600608,
      66600607,
      66600605,
      66600598,
      66600588,
      66600568,
      66600529,
      66600453,
      66600308,
      66600018,
      66599448,
      66598328,
      66596127,
      66591801,
      66583149,
      66565990,
      66531962,
      66464476,
      66330624,
      66065121,
      65534115,
      64476429,
      62369709,
      58173428,
      49814894,
      33165312
    ],
    "maxP": 66600612,
    "ssd": false,
    "collision_optimized": "Collision detected involving 66600605"
  },
  "29": {
    "n": 29,
    "P": [
      132931236,
      132931233,
      132931232,
      132931231,
      132931229,
      132931222,
      132931212,
      132931192,
      132931153,
      132931077,
      132930932,
      132930642,
      132930072,
      132928952,
      132926751,
      132922425,
      132913773,
      132896614,
      132862586,
      132795100,
      132661248,
      132395745,
      131864739,
      130807053,
      128700333,
      124504052,
      116145518,
      99495936,
      66330624
    ],
    "maxP": 132931236,
    "ssd": false,
    "collision_optimized": "Collision detected involving 132931229"
  },
  "30": {
    "n": 30,
    "P": [
      265326981,
      265326978,
      265326977,
      265326976,
      265326974,
      265326967,
      265326957,
      265326937,
      265326898,
      265326822,
      265326677,
      265326387,
      265325817,
      265324697,
      265322496,
      265318170,
      265309518,
      265292359,
      265258331,
      265190845,
      265056993,
      264791490,
      264260484,
      263202798,
      261096078,
      256899797,
      248541263,
      231891681,
      198726369,
      132395745
    ],
    "maxP": 265326981,
    "ssd": false,
    "collision_optimized": "Collision detected involving 265326974"
  }
}